{
  "global": {
    "Primary": {
      "Primary-900": {
        "value": "#331100",
        "type": "color",
        "description": "Tokens\n\nbackground-button-pressed"
      },
      "Primary-700": {
        "value": "#993300",
        "type": "color",
        "description": "Tokens\n\nbackground-button-pressed"
      },
      "Primary-500": {
        "value": "#00ffd5",
        "type": "color",
        "description": "Tokens\n\nbackground-button-pressed"
      },
      "Primary-300": {
        "value": "#ff9966",
        "type": "color",
        "description": "Tokens\n\nbackground-button-pressed"
      },
      "Primary-100": {
        "value": "#ffddcc",
        "type": "color",
        "description": "Tokens\n\nbackground-button-pressed"
      }
    },
    "Secondary": {
      "Secondary-900": {
        "value": "#031725",
        "type": "color"
      },
      "Secondary-700": {
        "value": "#0a436c",
        "type": "color"
      },
      "Secondary-500": {
        "value": "#106eb0",
        "type": "color"
      },
      "Secondary-300": {
        "value": "#52aeef",
        "type": "color"
      },
      "Secondary-100": {
        "value": "#c7e5fa",
        "type": "color"
      }
    },
    "Neutral": {
      "Neutral-900": {
        "value": "#0f0f0f",
        "type": "color"
      },
      "Neutral-800": {
        "value": "#1f1f1f",
        "type": "color"
      },
      "Neutral-700": {
        "value": "#404040",
        "type": "color"
      },
      "Neutral-600": {
        "value": "#808080",
        "type": "color"
      },
      "Neutral-500": {
        "value": "#9e9e9e",
        "type": "color"
      },
      "Neutral-400": {
        "value": "#b3b3b3",
        "type": "color"
      },
      "Neutral-300": {
        "value": "#c4c4c4",
        "type": "color"
      },
      "Neutral-200": {
        "value": "#d9d9d9",
        "type": "color"
      },
      "Neutral-100": {
        "value": "#ebebeb",
        "type": "color"
      },
      "Neutral-50": {
        "value": "#f5f5f5",
        "type": "color"
      }
    },
    "Semantic": {
      "Error": {
        "Error-900": {
          "value": "#570521",
          "type": "color"
        },
        "Error-700": {
          "value": "#830e22",
          "type": "color"
        },
        "Error-500": {
          "value": "#b71c1c",
          "type": "color"
        },
        "Error-300": {
          "value": "#ff9966",
          "type": "color"
        },
        "Error-100": {
          "value": "#fbdfd0",
          "type": "color"
        }
      },
      "Warning": {
        "Warning-900": {
          "value": "#733f09",
          "type": "color"
        },
        "Warning-700": {
          "value": "#ad6f17",
          "type": "color"
        },
        "Warning-500": {
          "value": "#f1ae2f",
          "type": "color"
        },
        "Warning-300": {
          "value": "#fad981",
          "type": "color"
        },
        "Warning-100": {
          "value": "#fef5d5",
          "type": "color"
        }
      },
      "Success": {
        "Success-900": {
          "value": "#003a39",
          "type": "color"
        },
        "Success-700": {
          "value": "#005744",
          "type": "color"
        },
        "Success-500": {
          "value": "#007a47",
          "type": "color"
        },
        "Success-300": {
          "value": "#56d787",
          "type": "color"
        },
        "Success-100": {
          "value": "#c6f8cf",
          "type": "color"
        }
      },
      "Info": {
        "Info-900": {
          "value": "#002033",
          "type": "color"
        },
        "Info-700": {
          "value": "#006199",
          "type": "color"
        },
        "Info-500": {
          "value": "#00a1ff",
          "type": "color"
        },
        "Info-300": {
          "value": "#66c7ff",
          "type": "color"
        },
        "Info-100": {
          "value": "#ccecff",
          "type": "color"
        }
      }
    },
    "Accent": {
      "Accent-900": {
        "value": "#331100",
        "type": "color"
      },
      "Accent-700": {
        "value": "#993300",
        "type": "color"
      },
      "Accent-500": {
        "value": "#ff5500",
        "type": "color"
      },
      "Accent-300": {
        "value": "#ff9966",
        "type": "color"
      },
      "Accent-100": {
        "value": "#ffddcc",
        "type": "color"
      }
    }
  },
  "$themes": [],
  "$metadata": {
    "tokenSetOrder": [
      "global"
    ]
  }
}